myriagon/__init__.py
myriagon/__main__.py
myriagon/_tasks.py
myriagon/_time.py
myriagon/_trash.py
myriagon/_version.py
myriagon/app.py
myriagon-16.10.0.dist-info/DESCRIPTION.rst
myriagon-16.10.0.dist-info/METADATA
myriagon-16.10.0.dist-info/RECORD
myriagon-16.10.0.dist-info/WHEEL
myriagon-16.10.0.dist-info/entry_points.txt
myriagon-16.10.0.dist-info/metadata.json
myriagon-16.10.0.dist-info/top_level.txt
